ojd_daps_skills/__init__.py
ojd_daps_skills/configs/extract_skills_esco.yaml
ojd_daps_skills/configs/extract_skills_lightcast.yaml
ojd_daps_skills/configs/extract_skills_template.yaml
ojd_daps_skills/configs/extract_skills_toy.yaml
ojd_daps_skills/data/esco_v_1_1_1_data_formatted.csv
ojd_daps_skills/data/esco_v_1_1_1_hier_mapper.json
ojd_daps_skills/data/hardcoded_ojo_esco_lookup.json
ojd_daps_skills/data/lightcast_data_formatted.csv
ojd_daps_skills/data/lightcast_hier_mapper.json
ojd_daps_skills/data/ojo_esco_lookup_sample.json
ojd_daps_skills/data/toy_data_formatted.csv
ojd_daps_skills/data/toy_hier_mapper.json
ojd_daps_skills/extract_skills/README.md
ojd_daps_skills/extract_skills/__init__.py
ojd_daps_skills/extract_skills/extract_skills.py
ojd_daps_skills/extract_skills/extract_skills_utils.py
ojd_daps_skills/extract_skills/multiskill_rules.py
ojd_daps_skills/map_skills/README.md
ojd_daps_skills/map_skills/__init__.py
ojd_daps_skills/map_skills/format_taxonomy/esco_formatting.py
ojd_daps_skills/map_skills/format_taxonomy/hard_coded_mapper_formatting.py
ojd_daps_skills/map_skills/format_taxonomy/lightcast_formatting.py
ojd_daps_skills/map_skills/skill_mapper.py
ojd_daps_skills/map_skills/skill_mapper_utils.py
ojd_daps_skills/utils/__init__.py
ojd_daps_skills/utils/bert_vectorizer.py
ojd_daps_skills/utils/data_getters.py
ojd_daps_skills/utils/esco_transversal_mapper.json
ojd_daps_skills/utils/text_cleaning.py
ojd_daps_skills-3.0.0.dist-info/LICENSE
ojd_daps_skills-3.0.0.dist-info/METADATA
ojd_daps_skills-3.0.0.dist-info/WHEEL
ojd_daps_skills-3.0.0.dist-info/RECORD
