Metadata-Version: 2.1
Name: ojd-daps-skills
Version: 3.0.0
Summary: An NLP package to extract skills from job adverts.
Author: Nesta
Author-email: dataanalytics@nesta.org.uk
Requires-Python: >=3.9,<4.0
Classifier: Programming Language :: Python :: 3
Classifier: Programming Language :: Python :: 3.9
Classifier: Programming Language :: Python :: 3.10
Classifier: Programming Language :: Python :: 3.11
Classifier: Programming Language :: Python :: 3.12
Requires-Dist: boto3 (>=1.34.99,<2.0.0)
Requires-Dist: botocore (>=1.34.99,<2.0.0)
Requires-Dist: numpy (>=1.26.4,<2.0.0)
Requires-Dist: pandas (>=2.2.2,<3.0.0)
Requires-Dist: pydantic (>=2.7.1,<3.0.0)
Requires-Dist: pytest (>=8.2.0,<9.0.0)
Requires-Dist: pyyaml (>=6.0.1,<7.0.0)
Requires-Dist: scikit-learn (>=1.4.2,<2.0.0)
Requires-Dist: sentence-transformers (>=2.1.0,<3.0.0)
Requires-Dist: skops (>=0.9.0,<0.10.0)
Requires-Dist: spacy (>=3.7.4,<3.8.0)
Requires-Dist: toolz (>=0.12.1,<0.13.0)
Requires-Dist: torch (>=1.13.1,<2.0.0)
Requires-Dist: transformers (==4.41.2)
